chat_companion/__init__.py
chat_companion/chat_commands.py
chat_companion/companion.py
chat_companion/log/companion_0.log
toolbox/__init__.py
toolbox/companion_logger.py
toolbox/prompt_tools.py
chat_companion-0.2.0.dist-info/LICENSE
chat_companion-0.2.0.dist-info/METADATA
chat_companion-0.2.0.dist-info/WHEEL
chat_companion-0.2.0.dist-info/entry_points.txt
chat_companion-0.2.0.dist-info/RECORD
