Metadata-Version: 2.1
Name: chat-companion
Version: 0.2.0
Summary: A chat gpt command line client with extra features"
License: Apache 2.0
Author: daniel-davee
Author-email: daniel.v.davee@gmail.com
Requires-Python: >=3.8,<4.0
Classifier: License :: Other/Proprietary License
Classifier: Programming Language :: Python :: 3
Classifier: Programming Language :: Python :: 3.8
Classifier: Programming Language :: Python :: 3.9
Classifier: Programming Language :: Python :: 3.10
Classifier: Programming Language :: Python :: 3.11
Requires-Dist: bardapi (>=0.1.38,<0.2.0)
Requires-Dist: icecream (>=2.1.3,<3.0.0)
Requires-Dist: inquirerpy (>=0.3.4,<0.4.0)
Requires-Dist: openai (>=0.26.5,<0.27.0)
Requires-Dist: plac (>=1.3.5,<2.0.0)
Requires-Dist: pysimplelog (>=4.0.0,<5.0.0)
